llama_index/readers/iceberg/__init__.py
llama_index/readers/iceberg/base.py
llama_index_readers_iceberg-0.4.1.dist-info/METADATA
llama_index_readers_iceberg-0.4.1.dist-info/WHEEL
llama_index_readers_iceberg-0.4.1.dist-info/licenses/LICENSE
llama_index_readers_iceberg-0.4.1.dist-info/RECORD
