Metadata-Version: 2.4
Name: llama-index-readers-iceberg
Version: 0.4.1
Summary: llama-index readers iceberg integration
Author-email: Abhijeeth Padarthi <abhijeeth@fivetran.com>
License-Expression: MIT
License-File: LICENSE
Requires-Python: <4.0,>=3.9
Requires-Dist: llama-index-core<0.15,>=0.13.0
Requires-Dist: pyiceberg<0.7,>=0.6.1
